<PAMDataset>
  <PAMRasterBand band="1">
    <Description>NDVI_2006</Description>
    <Histograms>
      <HistItem>
        <HistMin>-0.3993825018405914</HistMin>
        <HistMax>0.9304676651954651</HistMax>
        <BucketCount>256</BucketCount>
        <IncludeOutOfRange>1</IncludeOutOfRange>
        <Approximate>0</Approximate>
        <HistCounts>1|0|0|0|0|0|0|0|0|0|0|0|0|0|0|0|0|0|0|0|0|0|0|0|0|0|1|1|2|1|0|9|1|10|2|15|24|8|36|27|0|87|0|44|55|22|87|11|5|82|58|39|41|30|72|94|41|32|81|50|111|25|43|159|49|41|124|42|69|149|57|133|77|109|99|101|194|127|108|160|332|160|166|418|402|251|204|597|393|337|590|471|381|455|681|412|465|477|539|379|419|397|474|493|419|425|384|356|452|380|318|346|262|311|273|276|304|242|274|262|284|249|237|202|222|222|227|213|199|193|203|191|166|162|184|160|167|172|147|166|149|149|185|167|138|144|163|146|171|149|124|137|148|140|122|135|140|135|140|156|132|143|127|135|135|130|131|117|130|148|128|175|131|176|160|145|136|161|155|169|175|166|174|178|172|195|171|164|191|185|204|199|215|236|240|241|245|253|274|261|274|295|281|294|345|321|316|387|381|367|432|411|403|431|438|437|494|547|538|586|590|593|611|647|647|659|711|739|742|790|799|857|892|917|1005|1065|1137|1221|1183|1224|1309|1197|1248|1191|1007|853|711|518|368|279|118|65|20|9|3|1</HistCounts>
      </HistItem>
    </Histograms>
    <Metadata>
      <MDI key="name">NDVI_2006</MDI>
      <MDI key="STATISTICS_COVARIANCES">0.1013080067515665</MDI>
      <MDI key="STATISTICS_EXCLUDEDVALUES"></MDI>
      <MDI key="STATISTICS_MAXIMUM">0.93046766519547</MDI>
      <MDI key="STATISTICS_MEAN">0.52691884533529</MDI>
      <MDI key="STATISTICS_MEDIAN">0.659283</MDI>
      <MDI key="STATISTICS_MINIMUM">-0.39938250184059</MDI>
      <MDI key="STATISTICS_SKIPFACTORX">1</MDI>
      <MDI key="STATISTICS_SKIPFACTORY">1</MDI>
      <MDI key="STATISTICS_STDDEV">0.31828918729917</MDI>
    </Metadata>
  </PAMRasterBand>
</PAMDataset>
